SIHTTPRequest.py
SIHTTPRequest-18.2.1.dist-info/DESCRIPTION.rst
SIHTTPRequest-18.2.1.dist-info/METADATA
SIHTTPRequest-18.2.1.dist-info/RECORD
SIHTTPRequest-18.2.1.dist-info/WHEEL
SIHTTPRequest-18.2.1.dist-info/metadata.json
SIHTTPRequest-18.2.1.dist-info/top_level.txt
