Metadata-Version: 2.0
Name: SIHTTPRequest
Version: 18.2.1
Summary: This module helps to send request from client side to API, hosted on SimpleIntelligence.com
Home-page: UNKNOWN
Author: Simple Intelligence
Author-email: dev@simpleintelligence.com
License: Apache License, Version 2.0
Platform: UNKNOWN
